<?xml version="1.0" encoding="UTF-8"?>
<openbox_config xmlns="http://openbox.org/3.4/rc" xmlns:xi="http://www.w3.org/2001/XInclude">
  <resistance>
    <strength>10</strength>
    <screen_edge_strength>20</screen_edge_strength>
  </resistance>
  <focus>
    <focusNew>yes</focusNew>
    <followMouse>yes</followMouse>
    <focusLast>yes</focusLast>
    <underMouse>no</underMouse>
    <focusDelay>200</focusDelay>
    <raiseOnFocus>no</raiseOnFocus>
  </focus>
  <placement>
    <policy>Smart</policy>
    <center>yes</center>
    <monitor>Primary</monitor>
    <primaryMonitor>1</primaryMonitor>
  </placement>
  <theme>
    <name>Numix-Default</name>
    <titleLayout>IMC</titleLayout>
    <keepBorder>yes</keepBorder>
    <animateIconify>yes</animateIconify>
    <font place="ActiveWindow">
      <name>SFNS Display</name>
      <size>8</size>
      <weight>Normal</weight>
      <slant>Normal</slant>
    </font>
    <font place="InactiveWindow">
      <name>SFNS Display</name>
      <size>8</size>
      <weight>Normal</weight>
      <slant>Normal</slant>
    </font>
    <font place="MenuHeader">
      <name>Roboto Condensed,</name>
      <size>8</size>
      <weight>Normal</weight>
      <slant>Normal</slant>
    </font>
    <font place="MenuItem">
      <name>Roboto Condensed,</name>
      <size>8</size>
      <weight>Bold</weight>
      <slant>Normal</slant>
    </font>
    <font place="ActiveOnScreenDisplay">
      <name>SFNS Display</name>
      <size>8</size>
      <weight>Normal</weight>
      <slant>Normal</slant>
    </font>
    <font place="InactiveOnScreenDisplay">
      <name>SFNS Display</name>
      <size>8</size>
      <weight>Normal</weight>
      <slant>Normal</slant>
    </font>
  </theme>
  <desktops>
    <number>4</number>
    <firstdesk>1</firstdesk>
    <names>
      <name>1</name>
      <name>2</name>
      <name>3</name>
      <name>4</name>
    </names>
    <popupTime>875</popupTime>
  </desktops>
  <resize>
    <drawContents>yes</drawContents>
    <popupShow>Nonpixel</popupShow>
    <!-- 'Always', 'Never', or 'Nonpixel' (xterms and such) -->
    <popupPosition>Center</popupPosition>
    <popupFixedPosition>
      <x>10</x>
      <y>10</y>
    </popupFixedPosition>
  </resize>
  <margins>
    <top>0</top>
    <bottom>0</bottom>
    <left>0</left>
    <right>0</right>
  </margins>
  <dock>
    <position>TopLeft</position>
    <!-- (Top|Bottom)(Left|Right|)|Top|Bottom|Left|Right|Floating -->
    <floatingX>0</floatingX>
    <floatingY>0</floatingY>
    <noStrut>no</noStrut>
    <stacking>Above</stacking>
    <!-- 'Above', 'Normal', or 'Below' -->
    <direction>Vertical</direction>
    <!-- 'Vertical' or 'Horizontal' -->
    <autoHide>no</autoHide>
    <hideDelay>300</hideDelay>
    <!-- in milliseconds (1000 = 1 second) -->
    <showDelay>300</showDelay>
    <!-- in milliseconds (1000 = 1 second) -->
    <moveButton>Middle</moveButton>
    <!-- 'Left', 'Middle', 'Right' -->
  </dock>
  <keyboard>
    <chainQuitKey>C-g</chainQuitKey>
    <!-- Keybindings for desktop switching -->
    <keybind key="C-A-Left">
      <action name="GoToDesktop">
        <to>left</to>
        <wrap>no</wrap>
      </action>
    </keybind>
    <keybind key="C-A-Right">
      <action name="GoToDesktop">
        <to>right</to>
        <wrap>no</wrap>
      </action>
    </keybind>
    <keybind key="W-F1">
      <action name="GoToDesktop">
        <to>1</to>
      </action>
    </keybind>
    <keybind key="W-F2">
      <action name="GoToDesktop">
        <to>2</to>
      </action>
    </keybind>
    <keybind key="W-F3">
      <action name="GoToDesktop">
        <to>3</to>
      </action>
    </keybind>
    <keybind key="W-F4">
      <action name="GoToDesktop">
        <to>4</to>
      </action>
    </keybind>
    <keybind key="W-d">
      <action name="ToggleShowDesktop"/>
    </keybind>
    <!-- Keybindings for windows -->
    <keybind key="W-w">
      <action name="Close"/>
    </keybind>
    <keybind key="W-Escape">
      <action name="Lower"/>
      <action name="FocusToBottom"/>
      <action name="Unfocus"/>
    </keybind>
    <!-- Keybindings for window switching -->
    <keybind key="A-Tab">
      <action name="NextWindow">
		<dialog>icons</dialog>
        <finalactions>
          <action name="Focus"/>
          <action name="Raise"/>
          <action name="Unshade"/>
        </finalactions>
      </action>
    </keybind>
    <keybind key="W-g">
      <action name="Focus"/>
      <action name="Raise"/>
      <action name="Unshade"/>
      <action name="MoveResizeTo">
        <x>center</x>
        <y>center</y>
      </action>
    </keybind>
    <!-- Window Tiling: Snap feature -->
    <keybind key="W-Left">
      <action name="UnmaximizeFull"/>
      <action name="MaximizeVert"/>
      <action name="MoveResizeTo">
        <width>50%</width>
      </action>
      <action name="MoveToEdgeWest"/>
    </keybind>
    <keybind key="W-Right">
      <action name="UnmaximizeFull"/>
      <action name="MaximizeVert"/>
      <action name="MoveResizeTo">
        <width>50%</width>
      </action>
      <action name="MoveToEdgeEast"/>
    </keybind>
    <keybind key="W-Up">
      <action name="MaximizeFull"/>
    </keybind>
    <keybind key="W-Down">
      <action name="UnmaximizeFull"/>
    </keybind>
    <keybind key="W-S-Right">
      <action name="Unmaximize"/>
      <action name="MoveResizeTo">
        <x>-15</x>
        <y>15</y>
        <height>96%</height>
        <width>47%</width>
      </action>
    </keybind>
    <keybind key="W-S-Left">
      <action name="Unmaximize"/>
      <action name="MoveResizeTo">
        <x>15</x>
        <y>15</y>
        <height>96%</height>
        <width>47%</width>
      </action>
    </keybind>
    <!-- Top right-->
    <keybind key="W-k">
      <action name="Unmaximize"/>
      <action name="MoveResizeTo">
        <x>-15</x>
        <y>15</y>
      </action>
    </keybind>
    <!-- Top left-->
    <keybind key="W-h">
      <action name="Unmaximize"/>
      <action name="MoveResizeTo">
        <x>15</x>
        <y>15</y>
      </action>
    </keybind>
    <!-- Bottom left-->
    <keybind key="W-j">
      <action name="Unmaximize"/>
      <action name="MoveResizeTo">
        <x>15</x>
        <y>-15</y>
      </action>
    </keybind>
    <!-- Bottom right-->
    <keybind key="W-l">
      <action name="Unmaximize"/>
      <action name="MoveResizeTo">
        <x>-15</x>
        <y>-15</y>
      </action>
    </keybind>
    <keybind key="W-z">
      <action name="Unmaximize"/>
      <action name="MoveResizeTo">
        <x>15</x>
        <y>15</y>
        <height>97%</height>
        <width>32%</width>
      </action>
    </keybind>
    <keybind key="W-x">
      <action name="Unmaximize"/>
      <action name="MoveResizeTo">
        <x>34%</x>
        <y>15</y>
        <height>97%</height>
        <width>32%</width>
      </action>
    </keybind>
    <keybind key="W-c">
      <action name="Unmaximize"/>
      <action name="MoveResizeTo">
        <x>-17</x>
        <y>15</y>
        <height>97%</height>
        <width>32%</width>
      </action>
    </keybind>
    <!-- Keybindings for running applications -->
    <keybind key="XF86AudioRaiseVolume">
      <action name="Execute">
        <command>pactl set-sink-volume 0 +5%</command>
      </action>
    </keybind>
    <keybind key="XF86AudioLowerVolume">
      <action name="Execute">
        <command>pactl set-sink-volume 0 -5%</command>
      </action>
    </keybind>
    <keybind key="XF86MonBrightnessUp">
      <action name="Execute">
        <command>xbacklight -inc 5</command>
      </action>
    </keybind>
    <keybind key="XF86MonBrightnessDown">
      <action name="Execute">
        <command>xbacklight -dec 5</command>
      </action>
    </keybind>
    <keybind key="C-A-Delete">
      <action name="Execute">
        <command>oblogout</command>
      </action>
    </keybind>
    <keybind key="W-Return">
      <action name="Execute">
        <command>urxvt</command>
      </action>
    </keybind>
    <keybind key="W-f">
      <action name="Execute">
        <command>nautilus</command>
      </action>
    </keybind>
    <keybind key="W-space">
      <action name="Execute">
        <command>rofi -show drun</command>
      </action>
    </keybind>
    <keybind key="W-S-r">
      <action name="Execute">
        <command>openbox --restart</command>
      </action>
    </keybind>
    <keybind key="Print">
      <action name="Execute">
        <enabled>true</enabled>
        <command>bash ~/wms/bin/shot</command>
      </action>
    </keybind>
  </keyboard>
  <mouse>
    <dragThreshold>1</dragThreshold>
    <doubleClickTime>500</doubleClickTime>
    <screenEdgeWarpTime>400</screenEdgeWarpTime>
    <screenEdgeWarpMouse>false</screenEdgeWarpMouse>
    <context name="Frame">
      <mousebind button="A-Left" action="Press">
        <action name="Focus"/>
        <action name="Raise"/>
      </mousebind>
      <mousebind button="A-Left" action="Click">
        <action name="Unshade"/>
      </mousebind>
      <mousebind button="A-Left" action="Drag">
        <action name="Move"/>
      </mousebind>
      <mousebind button="A-Right" action="Press">
        <action name="Focus"/>
        <action name="Raise"/>
        <action name="Unshade"/>
      </mousebind>
      <mousebind button="A-Right" action="Drag">
        <action name="Resize"/>
      </mousebind>
      <mousebind button="A-Middle" action="Press">
        <action name="Lower"/>
        <action name="FocusToBottom"/>
        <action name="Unfocus"/>
      </mousebind>
      <mousebind button="A-Up" action="Click">
        <action name="GoToDesktop">
          <to>previous</to>
        </action>
      </mousebind>
      <mousebind button="A-Down" action="Click">
        <action name="GoToDesktop">
          <to>next</to>
        </action>
      </mousebind>
      <mousebind button="C-A-Up" action="Click">
        <action name="GoToDesktop">
          <to>previous</to>
        </action>
      </mousebind>
      <mousebind button="C-A-Down" action="Click">
        <action name="GoToDesktop">
          <to>next</to>
        </action>
      </mousebind>
      <mousebind button="A-S-Up" action="Click">
        <action name="SendToDesktop">
          <to>previous</to>
        </action>
      </mousebind>
      <mousebind button="A-S-Down" action="Click">
        <action name="SendToDesktop">
          <to>next</to>
        </action>
      </mousebind>
    </context>
    <context name="Titlebar">
      <mousebind button="Left" action="Drag">
        <action name="Move"/>
      </mousebind>
      <mousebind button="Left" action="DoubleClick">
        <action name="ToggleMaximizeFull"/>
      </mousebind>
      <mousebind button="Up" action="Click">
        <action name="if">
          <shaded>no</shaded>
          <then>
            <action name="Shade"/>
            <action name="FocusToBottom"/>
            <action name="Unfocus"/>
            <action name="Lower"/>
          </then>
        </action>
      </mousebind>
      <mousebind button="Down" action="Click">
        <action name="if">
          <shaded>yes</shaded>
          <then>
            <action name="Unshade"/>
            <action name="Raise"/>
          </then>
        </action>
      </mousebind>
    </context>
    <context name="Titlebar Top Right Bottom Left TLCorner TRCorner BRCorner BLCorner">
      <mousebind button="Left" action="Press">
        <action name="Focus"/>
        <action name="Raise"/>
        <action name="Unshade"/>
      </mousebind>
      <mousebind button="Middle" action="Press">
        <action name="Lower"/>
        <action name="FocusToBottom"/>
        <action name="Unfocus"/>
      </mousebind>
      <mousebind button="Right" action="Press">
        <action name="Focus"/>
        <action name="Raise"/>
        <action name="ShowMenu">
          <menu>client-menu</menu>
        </action>
      </mousebind>
    </context>
    <context name="Top">
      <mousebind button="Left" action="Drag">
        <action name="Resize">
          <edge>top</edge>
        </action>
      </mousebind>
    </context>
    <context name="Left">
      <mousebind button="Left" action="Drag">
        <action name="Resize">
          <edge>left</edge>
        </action>
      </mousebind>
    </context>
    <context name="Right">
      <mousebind button="Left" action="Drag">
        <action name="Resize">
          <edge>right</edge>
        </action>
      </mousebind>
    </context>
    <context name="Bottom">
      <mousebind button="Left" action="Drag">
        <action name="Resize">
          <edge>bottom</edge>
        </action>
      </mousebind>
      <mousebind button="Right" action="Press">
        <action name="Focus"/>
        <action name="Raise"/>
        <action name="ShowMenu">
          <menu>client-menu</menu>
        </action>
      </mousebind>
    </context>
    <context name="TRCorner BRCorner TLCorner BLCorner">
      <mousebind button="Left" action="Press">
        <action name="Focus"/>
        <action name="Raise"/>
        <action name="Unshade"/>
      </mousebind>
      <mousebind button="Left" action="Drag">
        <action name="Resize"/>
      </mousebind>
    </context>
    <context name="Client">
      <mousebind button="Left" action="Press">
        <action name="Focus"/>
        <action name="Raise"/>
      </mousebind>
      <mousebind button="Middle" action="Press">
        <action name="Focus"/>
        <action name="Raise"/>
      </mousebind>
      <mousebind button="Right" action="Press">
        <action name="Focus"/>
        <action name="Raise"/>
      </mousebind>
    </context>
    <context name="Icon">
      <mousebind button="Left" action="Press">
        <action name="Focus"/>
        <action name="Raise"/>
        <action name="Unshade"/>
        <action name="ShowMenu">
          <menu>client-menu</menu>
        </action>
      </mousebind>
      <mousebind button="Right" action="Press">
        <action name="Focus"/>
        <action name="Raise"/>
        <action name="ShowMenu">
          <menu>client-menu</menu>
        </action>
      </mousebind>
    </context>
    <context name="AllDesktops">
      <mousebind button="Left" action="Press">
        <action name="Focus"/>
        <action name="Raise"/>
        <action name="Unshade"/>
      </mousebind>
      <mousebind button="Left" action="Click">
        <action name="ToggleOmnipresent"/>
      </mousebind>
    </context>
    <context name="Shade">
      <mousebind button="Left" action="Press">
        <action name="Focus"/>
        <action name="Raise"/>
      </mousebind>
      <mousebind button="Left" action="Click">
        <action name="ToggleShade"/>
      </mousebind>
    </context>
    <context name="Iconify">
      <mousebind button="Left" action="Press">
        <action name="Focus"/>
        <action name="Raise"/>
      </mousebind>
      <mousebind button="Left" action="Click">
        <action name="Iconify"/>
      </mousebind>
    </context>
    <context name="Maximize">
      <mousebind button="Left" action="Press">
        <action name="Focus"/>
        <action name="Raise"/>
        <action name="Unshade"/>
      </mousebind>
      <mousebind button="Middle" action="Press">
        <action name="Focus"/>
        <action name="Raise"/>
        <action name="Unshade"/>
      </mousebind>
      <mousebind button="Right" action="Press">
        <action name="Focus"/>
        <action name="Raise"/>
        <action name="Unshade"/>
      </mousebind>
      <mousebind button="Left" action="Click">
        <action name="ToggleMaximize"/>
      </mousebind>
      <mousebind button="Middle" action="Click">
        <action name="ToggleMaximize">
          <direction>vertical</direction>
        </action>
      </mousebind>
      <mousebind button="Right" action="Click">
        <action name="ToggleMaximize">
          <direction>horizontal</direction>
        </action>
      </mousebind>
    </context>
    <context name="Close">
      <mousebind button="Left" action="Press">
        <action name="Focus"/>
        <action name="Raise"/>
        <action name="Unshade"/>
      </mousebind>
      <mousebind button="Left" action="Click">
        <action name="Close"/>
      </mousebind>
    </context>
    <context name="Desktop">
      <mousebind button="Up" action="Click">
        <action name="GoToDesktop">
          <to>previous</to>
        </action>
      </mousebind>
      <mousebind button="Down" action="Click">
        <action name="GoToDesktop">
          <to>next</to>
        </action>
      </mousebind>
      <mousebind button="A-Up" action="Click">
        <action name="GoToDesktop">
          <to>previous</to>
        </action>
      </mousebind>
      <mousebind button="A-Down" action="Click">
        <action name="GoToDesktop">
          <to>next</to>
        </action>
      </mousebind>
      <mousebind button="C-A-Up" action="Click">
        <action name="GoToDesktop">
          <to>previous</to>
        </action>
      </mousebind>
      <mousebind button="C-A-Down" action="Click">
        <action name="GoToDesktop">
          <to>next</to>
        </action>
      </mousebind>
      <mousebind button="Left" action="Press">
        <action name="Focus"/>
        <action name="Raise"/>
      </mousebind>
      <mousebind button="Right" action="Press">
        <action name="Focus"/>
        <action name="Raise"/>
      </mousebind>
    </context>
    <context name="Root">
      <!-- Menus -->
      <mousebind button="Right" action="Press">
        <action name="ShowMenu">
          <menu>root-menu</menu>
        </action>
      </mousebind>
    </context>
  </mouse>
  <menu>
    <file>menu.xml</file>
    <hideDelay>200</hideDelay>
    <middle>no</middle>
    <submenuShowDelay>100</submenuShowDelay>
    <submenuHideDelay>400</submenuHideDelay>
    <showIcons>yes</showIcons>
    <manageDesktops>yes</manageDesktops>
  </menu>
</openbox_config>
